aes_bridge/__init__.py
aes_bridge/cbc.py
aes_bridge/common.py
aes_bridge/gcm.py
aes_bridge/legacy.py
aes_bridge-2.0.4.dist-info/licenses/LICENSE
tests/test_aes.py
aes_bridge-2.0.4.dist-info/METADATA
aes_bridge-2.0.4.dist-info/WHEEL
aes_bridge-2.0.4.dist-info/top_level.txt
aes_bridge-2.0.4.dist-info/RECORD
