Metadata-Version: 2.4
Name: aes-bridge
Version: 2.0.4
Summary: AesBridge is a modern, secure and cross-language AES encryption library
Author-email: Andrey Izman <izmanw@gmail.com>
License-Expression: MIT
Project-URL: Homepage, https://github.com/mervick/aes-bridge-python
Project-URL: BugTracker, https://github.com/mervick/aes-bridge-python/issues
Project-URL: Source, https://github.com/mervick/aes-bridge-python
Classifier: Operating System :: OS Independent
Classifier: Operating System :: Unix
Classifier: Operating System :: POSIX :: Linux
Classifier: Operating System :: Microsoft :: Windows
Classifier: Operating System :: MacOS :: MacOS X
Classifier: Programming Language :: Python :: 3
Classifier: Programming Language :: Python :: 3.10
Classifier: Programming Language :: Python :: 3.11
Classifier: Programming Language :: Python :: 3.12
Classifier: Topic :: Security :: Cryptography
Requires-Python: >=3.10
License-File: LICENSE
Requires-Dist: cryptography
Dynamic: license-file
